{
    "current_mode": "eye_grid_speech",
    "default": "idle_hand",
    "iteration_order": {
        "basic_hand": "touchpoints_hand",
        "basic_left_hand_speech": "touchpoints_left_hand_speech",
        "basic_right_hand_speech": "touchpoints_right_hand_speech",
        "exercise_equipment": "nose_grid_speech",
        "exercise_no_equipment": "exercise_equipment",
        "extremity_triggers": "nose_floating_speech",
        "eye_floating_facial": "speech",
        "eye_floating_speech": "eye_floating_facial",
        "eye_grid_facial": "nose_grid_facial",
        "eye_grid_speech": "eye_grid_facial",
        "gamepad_mode_1": "gamepad_mode_2",
        "gamepad_mode_2": "gamepad_mode_3",
        "gamepad_mode_3": "right_fps_mode_1",
        "idle_hand": "idle_hand",
        "idle_left_hand": "idle_left_hand",
        "idle_right_hand": "idle_right_hand",
        "joystick": "gamepad_mode_1",
        "left_fps_mode_1": "left_fps_mode_2",
        "left_fps_mode_2": "left_fps_mode_3",
        "left_fps_mode_3": "basic_hand",
        "nose_floating_facial": "eye_floating_speech",
        "nose_floating_speech": "nose_floating_facial",
        "nose_grid_facial": "joystick",
        "nose_grid_speech": "eye_grid_speech",
        "pen_hand": "extremity_triggers",
        "right_fps_mode_1": "right_fps_mode_2",
        "right_fps_mode_2": "right_fps_mode_3",
        "right_fps_mode_3": "left_fps_mode_1",
        "speech": "exercise_no_equipment",
        "touchpoints_hand": "pen_hand",
        "touchpoints_left_hand_speech": "basic_left_hand_speech",
        "touchpoints_right_hand_speech": "basic_right_hand_speech"
    },
    "mode_labels": {
        "basic_left_hand_speech": "CLASSIC MOUSE",
        "basic_right_hand_speech": "CLASSIC MOUSE",
        "eye_grid_facial": "EYE GAZE WITH FACIAL SWITCHES",
        "eye_grid_speech": "EYE GAZE WITH SPEECH",
        "idle_left_hand": "IDLE",
        "idle_right_hand": "IDLE",
        "nose_grid_facial": "NOSE NAVIGATION with FACIAL SWITCHES",
        "nose_grid_speech": "NOSE NAVIGATION WITH SPEECH",
        "touchpoints_left_hand_speech": "MULTITOUCH WITH SPEECH",
        "touchpoints_right_hand_speech": "MULTITOUCH WITH SPEECH"
    },
    "modes": {
        "basic_hand": [
            "hand_index_pinch_left_press_left_hand",
            "hand_middle_pinch_right_press_left_hand",
            "hand_index_pulldown_left_press_left_hand",
            "hand_pinky_pinch_monitor_change_left_hand",
            "general_rocknroll_next_mode",
            "hand_to_idle_mode_left_hand",
            "hand_palm_center_move_mouse_left_hand",
            "hand_fist_doubleclick_left_hand",
            "hand_palm_height_change_aoi_resize_left_hand",
            "hand_double_index_pinch_zoom",
            "hand_index_middle_scroll_left_hand",
            "hand_open_keyboard_left_hand"
        ],
        "basic_hand_speech": [
            "hand_index_pinch_left_press_left_hand",
            "speech_next_mode",
            "general_rocknroll_next_mode",
            "hand_pinky_pinch_monitor_change_left_hand",
            "hand_to_idle_mode_left_hand",
            "speech_keyboard_windows_key",
            "speech_keyboard_cut",
            "speech_keyboard_copy",
            "hand_open_keyboard_left_hand",
            "speech_double_clicking",
            "speech_keyboard_escape",
            "speech_keyboard_space",
            "speech_stop_transcribe",
            "speech_right_clicking",
            "speech_keyboard_page_up",
            "speech_keyboard_windows_run",
            "hand_middle_pinch_right_press_left_hand",
            "speech_hotkey_print",
            "hand_index_pulldown_left_press_left_hand",
            "speech_keyboard_left_arrow",
            "speech_hotkey_paste",
            "speech_keyboard_help",
            "speech_hotkey_revert",
            "speech_keyboard_macros",
            "speech_clicking",
            "hand_double_index_pinch_zoom",
            "speech_keyboard_page_down",
            "speech_keyboard_volume_up",
            "speech_keyboard_right_arrow",
            "speech_keyboard_volume_down",
            "speech_start_transcribe",
            "speech_hotkey_full_screen",
            "hand_palm_center_move_mouse_left_hand",
            "hand_fist_doubleclick_left_hand",
            "hand_palm_height_change_aoi_resize_left_hand",
            "speech_keyboard_switch",
            "speech_hotkey_save",
            "hand_index_middle_scroll_left_hand",
            "speech_hotkey_close",
            "speech_correction_mode_start",
            "speech_correction_mode_stop",
            "speech_start_speaker_identification",
            "speech_stop_speaker_identification",
            "speech_keyboard_backspace",
            "speech_keyboard_capital_letters",
            "speech_keyboard_hashtag"
        ],
        "basic_left_hand_speech": [
            "hand_index_pinch_left_press_left_hand",
            "hand_middle_pinch_right_press_left_hand",
            "hand_pinky_pinch_monitor_change_left_hand",
            "hand_to_idle_mode_left_hand",
            "hand_palm_center_move_mouse_left_hand",
            "hand_fist_doubleclick_left_hand",
            "hand_palm_height_change_aoi_resize_left_hand",
            "hand_double_index_pinch_zoom",
            "hand_index_middle_scroll_left_hand",
            "speech_keyboard_windows_key",
            "speech_keyboard_left_arrow",
            "speech_double_clicking",
            "speech_hotkey_paste",
            "speech_keyboard_space",
            "speech_keyboard_switch",
            "speech_keyboard_macros",
            "speech_hotkey_full_screen",
            "speech_right_clicking",
            "speech_keyboard_copy",
            "speech_right_release",
            "speech_hotkey_window_minimize",
            "speech_hotkey_windows_screenshot",
            "speech_hotkey_revert",
            "speech_keyboard_page_up",
            "speech_keyboard_windows_run",
            "speech_keyboard_page_down",
            "speech_hotkey_print",
            "speech_keyboard_help",
            "speech_hotkey_window_maximize_left",
            "speech_keyboard_windows_startmenu",
            "speech_right_press",
            "speech_keyboard_right_arrow",
            "speech_hotkey_close",
            "speech_left_press",
            "speech_clicking",
            "speech_keyboard_cut",
            "speech_stop_transcribe",
            "speech_change_language",
            "speech_hotkey_save",
            "speech_hotkey_window_maximize_right",
            "speech_hotkey_windows_explorer_files",
            "speech_keyboard_escape",
            "speech_hotkey_window_maximize",
            "speech_start_transcribe",
            "speech_keyboard_volume_down",
            "speech_left_release",
            "speech_keyboard_volume_up",
            "speech_next_mode",
            "speech_correction_mode_start",
            "speech_correction_mode_stop",
            "speech_start_speaker_identification",
            "speech_stop_speaker_identification",
            "speech_keyboard_backspace",
            "speech_keyboard_capital_letters",
            "speech_keyboard_hashtag",
            "speech_keyboard_settings",
            "speech_hotkey_go_left",
            "speech_hotkey_go_right",
            "speech_hotkey_remove"
        ],
        "basic_right_hand_speech": [
            "hand_index_pinch_left_press_right_hand",
            "hand_middle_pinch_right_press_right_hand",
            "hand_pinky_pinch_monitor_change_right_hand",
            "hand_to_idle_mode_right_hand",
            "hand_palm_center_move_mouse_right_hand",
            "hand_fist_doubleclick_right_hand",
            "hand_palm_height_change_aoi_resize_right_hand",
            "hand_double_index_pinch_zoom",
            "hand_index_middle_scroll_right_hand",
            "speech_keyboard_windows_key",
            "speech_keyboard_left_arrow",
            "speech_double_clicking",
            "speech_hotkey_paste",
            "speech_keyboard_space",
            "speech_keyboard_switch",
            "speech_keyboard_macros",
            "speech_hotkey_full_screen",
            "speech_right_clicking",
            "speech_keyboard_copy",
            "speech_right_release",
            "speech_hotkey_window_minimize",
            "speech_hotkey_windows_screenshot",
            "speech_hotkey_revert",
            "speech_keyboard_page_up",
            "speech_keyboard_windows_run",
            "speech_keyboard_page_down",
            "speech_hotkey_print",
            "speech_keyboard_help",
            "speech_hotkey_window_maximize_left",
            "speech_keyboard_windows_startmenu",
            "speech_right_press",
            "speech_keyboard_right_arrow",
            "speech_hotkey_close",
            "speech_left_press",
            "speech_clicking",
            "speech_keyboard_cut",
            "speech_stop_transcribe",
            "speech_hotkey_save",
            "speech_hotkey_window_maximize_right",
            "speech_hotkey_windows_explorer_files",
            "speech_keyboard_escape",
            "speech_hotkey_window_maximize",
            "speech_start_transcribe",
            "speech_change_language",
            "speech_keyboard_volume_down",
            "speech_left_release",
            "speech_keyboard_volume_up",
            "speech_next_mode",
            "speech_correction_mode_start",
            "speech_correction_mode_stop",
            "speech_start_speaker_identification",
            "speech_stop_speaker_identification",
            "speech_keyboard_backspace",
            "speech_keyboard_capital_letters",
            "speech_keyboard_hashtag",
            "speech_keyboard_settings",
            "speech_hotkey_go_left",
            "speech_hotkey_go_right",
            "speech_hotkey_remove"
        ],
        "exercise_equipment": [
            "general_rocknroll_next_mode",
            "exercise_bike",
            "exercise_rowing"
        ],
        "exercise_equipment_speech": [
            "general_rocknroll_next_mode",
            "speech_keyboard_windows_key",
            "speech_keyboard_cut",
            "speech_keyboard_copy",
            "speech_double_clicking",
            "speech_keyboard_escape",
            "speech_keyboard_space",
            "speech_stop_transcribe",
            "speech_right_clicking",
            "speech_keyboard_page_up",
            "exercise_bike",
            "speech_keyboard_windows_run",
            "speech_hotkey_print",
            "speech_keyboard_left_arrow",
            "speech_hotkey_paste",
            "speech_keyboard_help",
            "speech_hotkey_revert",
            "speech_keyboard_macros",
            "speech_clicking",
            "speech_keyboard_page_down",
            "speech_keyboard_volume_up",
            "exercise_rowing",
            "speech_keyboard_right_arrow",
            "speech_keyboard_volume_down",
            "speech_start_transcribe",
            "speech_hotkey_full_screen",
            "speech_keyboard_switch",
            "speech_hotkey_save",
            "speech_next_mode",
            "speech_hotkey_close",
            "speech_correction_mode_start",
            "speech_correction_mode_stop",
            "speech_keyboard_hashtag"
        ],
        "exercise_no_equipment": [
            "general_rocknroll_next_mode",
            "exercise_walking"
        ],
        "exercise_no_equipment_speech": [
            "general_rocknroll_next_mode",
            "speech_keyboard_windows_key",
            "exercise_walking",
            "speech_keyboard_cut",
            "speech_keyboard_copy",
            "speech_double_clicking",
            "speech_keyboard_escape",
            "speech_keyboard_space",
            "speech_stop_transcribe",
            "speech_right_clicking",
            "speech_keyboard_page_up",
            "speech_keyboard_windows_run",
            "speech_hotkey_print",
            "speech_keyboard_left_arrow",
            "speech_hotkey_paste",
            "speech_keyboard_help",
            "speech_hotkey_revert",
            "speech_keyboard_macros",
            "speech_clicking",
            "speech_keyboard_page_down",
            "speech_keyboard_volume_up",
            "speech_keyboard_right_arrow",
            "speech_keyboard_volume_down",
            "speech_start_transcribe",
            "speech_hotkey_full_screen",
            "speech_keyboard_switch",
            "speech_hotkey_save",
            "speech_next_mode",
            "speech_hotkey_close",
            "speech_correction_mode_start",
            "speech_correction_mode_stop",
            "speech_keyboard_hashtag"
        ],
        "extremity_triggers": [
            "general_rocknroll_next_mode"
        ],
        "extremity_triggers_speech": [
            "general_rocknroll_next_mode",
            "speech_keyboard_windows_key",
            "speech_keyboard_cut",
            "speech_keyboard_copy",
            "speech_double_clicking",
            "speech_keyboard_escape",
            "speech_keyboard_space",
            "speech_stop_transcribe",
            "speech_right_clicking",
            "speech_keyboard_page_up",
            "speech_keyboard_windows_run",
            "speech_hotkey_print",
            "speech_keyboard_left_arrow",
            "speech_hotkey_paste",
            "speech_keyboard_help",
            "speech_hotkey_revert",
            "speech_keyboard_macros",
            "speech_clicking",
            "speech_keyboard_page_down",
            "speech_keyboard_volume_up",
            "speech_keyboard_right_arrow",
            "speech_keyboard_volume_down",
            "speech_start_transcribe",
            "speech_hotkey_full_screen",
            "speech_keyboard_switch",
            "speech_hotkey_save",
            "speech_next_mode",
            "speech_hotkey_close",
            "speech_correction_mode_start",
            "speech_correction_mode_stop",
            "speech_keyboard_hashtag"
        ],
        "extremity_walking": [
            "general_rocknroll_next_mode",
            "extremity_walking_event"
        ],
        "extremity_walking_speech": [
            "general_rocknroll_next_mode",
            "speech_keyboard_windows_key",
            "speech_keyboard_cut",
            "speech_keyboard_copy",
            "speech_double_clicking",
            "speech_keyboard_escape",
            "speech_keyboard_space",
            "speech_stop_transcribe",
            "speech_right_clicking",
            "speech_keyboard_page_up",
            "speech_keyboard_windows_run",
            "speech_hotkey_print",
            "speech_keyboard_left_arrow",
            "speech_hotkey_paste",
            "speech_keyboard_help",
            "speech_hotkey_revert",
            "speech_keyboard_macros",
            "speech_clicking",
            "speech_keyboard_page_down",
            "speech_keyboard_volume_up",
            "speech_keyboard_right_arrow",
            "speech_keyboard_volume_down",
            "speech_start_transcribe",
            "speech_hotkey_full_screen",
            "speech_keyboard_switch",
            "speech_hotkey_save",
            "extremity_walking_event",
            "speech_next_mode",
            "speech_hotkey_close",
            "speech_correction_mode_start",
            "speech_correction_mode_stop",
            "speech_keyboard_hashtag"
        ],
        "eye_floating_facial": [
            "head_fishface_left_click",
            "head_raise_eyebrows_double_click",
            "general_rocknroll_next_mode",
            "head_eye_tracking",
            "head_open_mouth_double_click",
            "speech_next_mode",
            "head_smile_on_off_eye_gaze"
        ],
        "eye_floating_speech": [
            "general_rocknroll_next_mode",
            "speech_keyboard_windows_key",
            "speech_keyboard_cut",
            "speech_keyboard_copy",
            "speech_double_clicking",
            "speech_keyboard_escape",
            "speech_keyboard_space",
            "speech_stop_transcribe",
            "speech_right_clicking",
            "speech_keyboard_page_up",
            "head_eye_tracking",
            "speech_keyboard_windows_run",
            "speech_hotkey_print",
            "speech_keyboard_left_arrow",
            "speech_hotkey_paste",
            "speech_keyboard_enter",
            "speech_keyboard_up_arrow",
            "speech_keyboard_down_arrow",
            "speech_keyboard_help",
            "speech_hotkey_revert",
            "speech_keyboard_macros",
            "speech_clicking",
            "speech_keyboard_page_down",
            "speech_keyboard_volume_up",
            "speech_keyboard_right_arrow",
            "speech_keyboard_volume_down",
            "speech_start_transcribe",
            "speech_hotkey_full_screen",
            "speech_keyboard_switch",
            "speech_hotkey_save",
            "speech_next_mode",
            "speech_hotkey_close",
            "speech_left_press",
            "speech_left_release",
            "speech_right_press",
            "speech_right_release",
            "speech_correction_mode_start",
            "speech_correction_mode_stop",
            "speech_keyboard_hashtag"
        ],
        "eye_grid_facial": [
            "speech_next_mode",
            "general_rocknroll_next_mode",
            "head_eye_mode2",
            "head_open_mouth_double_click",
            "head_fishface_left_click",
            "head_eyebrows_on_off_eye_gaze",
            "head_smile_left_press_hold_release"
        ],
        "eye_grid_speech": [
            "general_rocknroll_next_mode",
            "speech_keyboard_windows_key",
            "speech_keyboard_cut",
            "speech_keyboard_copy",
            "speech_eye_start",
            "speech_cal_change",
            "speech_double_clicking",
            "speech_keyboard_escape",
            "speech_keyboard_space",
            "head_eye_mode2",
            "speech_stop_transcribe",
            "speech_right_clicking",
            "speech_keyboard_page_up",
            "speech_eye_magnet_go",
            "speech_keyboard_windows_run",
            "speech_hotkey_print",
            "speech_keyboard_left_arrow",
            "speech_hotkey_paste",
            "speech_keyboard_help",
            "speech_hotkey_revert",
            "speech_keyboard_enter",
            "speech_keyboard_up_arrow",
            "speech_keyboard_down_arrow",
            "speech_keyboard_macros",
            "speech_clicking",
            "speech_keyboard_page_down",
            "speech_keyboard_volume_up",
            "speech_keyboard_right_arrow",
            "speech_keyboard_volume_down",
            "speech_start_transcribe",
            "speech_change_language",
            "speech_hotkey_full_screen",
            "speech_keyboard_switch",
            "speech_hotkey_save",
            "speech_eye_stop",
            "speech_next_mode",
            "speech_hotkey_close",
            "speech_left_press",
            "speech_left_release",
            "speech_right_press",
            "speech_right_release",
            "speech_correction_mode_start",
            "speech_correction_mode_stop",
            "speech_start_speaker_identification",
            "speech_stop_speaker_identification",
            "speech_keyboard_hashtag"
        ],
        "gamepad_mode_1": [
            "general_rocknroll_next_mode",
            "gamepad_mode_1_event"
        ],
        "gamepad_mode_1_speech": [
            "general_rocknroll_next_mode",
            "speech_keyboard_windows_key",
            "speech_keyboard_cut",
            "speech_keyboard_copy",
            "speech_double_clicking",
            "speech_keyboard_escape",
            "speech_keyboard_space",
            "speech_stop_transcribe",
            "speech_right_clicking",
            "speech_keyboard_page_up",
            "speech_keyboard_windows_run",
            "speech_hotkey_print",
            "speech_keyboard_left_arrow",
            "speech_hotkey_paste",
            "speech_keyboard_help",
            "speech_hotkey_revert",
            "speech_keyboard_macros",
            "speech_clicking",
            "speech_keyboard_page_down",
            "speech_keyboard_volume_up",
            "speech_keyboard_right_arrow",
            "speech_keyboard_volume_down",
            "speech_start_transcribe",
            "speech_hotkey_full_screen",
            "speech_keyboard_switch",
            "gamepad_mode_1_event",
            "speech_hotkey_save",
            "speech_next_mode",
            "speech_hotkey_close",
            "speech_correction_mode_start",
            "speech_correction_mode_stop",
            "speech_keyboard_hashtag"
        ],
        "gamepad_mode_2": [
            "general_rocknroll_next_mode",
            "gamepad_mode_2_event"
        ],
        "gamepad_mode_2_speech": [
            "general_rocknroll_next_mode",
            "speech_keyboard_windows_key",
            "speech_keyboard_cut",
            "speech_keyboard_copy",
            "gamepad_mode_2_event",
            "speech_double_clicking",
            "speech_keyboard_escape",
            "speech_keyboard_space",
            "speech_stop_transcribe",
            "speech_right_clicking",
            "speech_keyboard_page_up",
            "speech_keyboard_windows_run",
            "speech_hotkey_print",
            "speech_keyboard_left_arrow",
            "speech_hotkey_paste",
            "speech_keyboard_help",
            "speech_hotkey_revert",
            "speech_keyboard_macros",
            "speech_clicking",
            "speech_keyboard_page_down",
            "speech_keyboard_volume_up",
            "speech_keyboard_right_arrow",
            "speech_keyboard_volume_down",
            "speech_start_transcribe",
            "speech_hotkey_full_screen",
            "speech_keyboard_switch",
            "speech_hotkey_save",
            "speech_next_mode",
            "speech_hotkey_close",
            "speech_correction_mode_start",
            "speech_correction_mode_stop",
            "speech_keyboard_hashtag"
        ],
        "gamepad_mode_3": [
            "general_rocknroll_next_mode",
            "gamepad_mode_3_event"
        ],
        "gamepad_mode_3_speech": [
            "general_rocknroll_next_mode",
            "speech_keyboard_windows_key",
            "speech_keyboard_cut",
            "speech_keyboard_copy",
            "speech_double_clicking",
            "speech_keyboard_escape",
            "speech_keyboard_space",
            "speech_stop_transcribe",
            "speech_right_clicking",
            "speech_keyboard_page_up",
            "gamepad_mode_3_event",
            "speech_keyboard_windows_run",
            "speech_hotkey_print",
            "speech_keyboard_left_arrow",
            "speech_hotkey_paste",
            "speech_keyboard_help",
            "speech_hotkey_revert",
            "speech_keyboard_macros",
            "speech_clicking",
            "speech_keyboard_page_down",
            "speech_keyboard_volume_up",
            "speech_keyboard_right_arrow",
            "speech_keyboard_volume_down",
            "speech_start_transcribe",
            "speech_hotkey_full_screen",
            "speech_keyboard_switch",
            "speech_hotkey_save",
            "speech_next_mode",
            "speech_hotkey_close",
            "speech_correction_mode_start",
            "speech_correction_mode_stop",
            "speech_keyboard_hashtag"
        ],
        "gun_click_left": [
            "gun_move_left_hand",
            "hand_index_pinch_left_press_right_hand"
        ],
        "gun_click_left_speech": [
            "general_rocknroll_next_mode",
            "speech_keyboard_windows_key",
            "speech_keyboard_cut",
            "speech_keyboard_copy",
            "speech_double_clicking",
            "speech_keyboard_escape",
            "speech_keyboard_space",
            "speech_stop_transcribe",
            "speech_right_clicking",
            "speech_keyboard_page_up",
            "speech_keyboard_windows_run",
            "speech_hotkey_print",
            "speech_keyboard_left_arrow",
            "speech_hotkey_paste",
            "speech_keyboard_help",
            "speech_hotkey_revert",
            "speech_keyboard_macros",
            "speech_clicking",
            "hand_index_pinch_left_press_right_hand",
            "speech_keyboard_page_down",
            "speech_keyboard_volume_up",
            "speech_keyboard_right_arrow",
            "speech_keyboard_volume_down",
            "speech_start_transcribe",
            "speech_hotkey_full_screen",
            "gun_move_left_hand",
            "speech_keyboard_switch",
            "speech_hotkey_save",
            "speech_next_mode",
            "speech_hotkey_close",
            "speech_correction_mode_start",
            "speech_correction_mode_stop",
            "speech_keyboard_hashtag"
        ],
        "gun_click_right": [
            "hand_index_pinch_left_press_left_hand",
            "gun_move_right_hand"
        ],
        "gun_click_right_speech": [
            "hand_index_pinch_left_press_left_hand",
            "general_rocknroll_next_mode",
            "speech_keyboard_windows_key",
            "speech_keyboard_cut",
            "speech_keyboard_copy",
            "speech_double_clicking",
            "speech_keyboard_escape",
            "speech_keyboard_space",
            "speech_stop_transcribe",
            "speech_right_clicking",
            "speech_keyboard_page_up",
            "speech_keyboard_windows_run",
            "gun_move_right_hand",
            "speech_hotkey_print",
            "speech_keyboard_left_arrow",
            "speech_hotkey_paste",
            "speech_keyboard_help",
            "speech_hotkey_revert",
            "speech_keyboard_macros",
            "speech_clicking",
            "speech_keyboard_page_down",
            "speech_keyboard_volume_up",
            "speech_keyboard_right_arrow",
            "speech_keyboard_volume_down",
            "speech_start_transcribe",
            "speech_hotkey_full_screen",
            "speech_keyboard_switch",
            "speech_hotkey_save",
            "speech_next_mode",
            "speech_hotkey_close",
            "speech_correction_mode_start",
            "speech_correction_mode_stop",
            "speech_keyboard_hashtag"
        ],
        "hand_drive": [
            "hand_drive_forward_backward",
            "hand_drive_left_right",
            "speech_ibm_polution_game_change",
            "speech_ibm_polution_game_remove",
            "speech_ibm_polution_game_tag"
        ],
        "hand_spiderman_thwip_left_hand": [
            "hand_spiderman_thwip_left_hand"
        ],
        "hand_spiderman_thwip_right_hand": [
            "hand_spiderman_thwip_right_hand"
        ],
        "idle_hand": [
            "hand_to_active_mode_right_hand"
        ],
        "idle_left_hand": [
            "hand_to_active_mode_left_hand"
        ],
        "idle_right_hand": [
            "hand_to_active_mode_right_hand"
        ],
        "joystick": [
            "joystick_stick_left",
            "joystick_stick_right",
            "joystick_button_back",
            "joystick_triggers_left",
            "joystick_shoulder_left",
            "general_rocknroll_next_mode",
            "joystick_shoulder_right",
            "joystick_button_y",
            "joystick_button_a",
            "joystick_button_x",
            "joystick_dpad_left",
            "joystick_dpad_right",
            "joystick_button_b",
            "joystick_triggers_right",
            "joystick_dpad_down",
            "joystick_button_start",
            "joystick_dpad_up"
        ],
        "joystick_speech": [
            "general_rocknroll_next_mode",
            "speech_keyboard_windows_key",
            "speech_keyboard_cut",
            "joystick_dpad_right",
            "speech_keyboard_copy",
            "joystick_dpad_left",
            "joystick_dpad_down",
            "joystick_button_start",
            "joystick_stick_left",
            "speech_double_clicking",
            "joystick_shoulder_left",
            "speech_keyboard_escape",
            "speech_keyboard_space",
            "speech_stop_transcribe",
            "joystick_button_a",
            "speech_keyboard_page_up",
            "speech_right_clicking",
            "joystick_triggers_right",
            "joystick_dpad_up",
            "speech_keyboard_windows_run",
            "speech_hotkey_print",
            "joystick_stick_right",
            "joystick_button_back",
            "speech_keyboard_left_arrow",
            "speech_hotkey_paste",
            "joystick_shoulder_right",
            "speech_keyboard_help",
            "joystick_button_y",
            "speech_hotkey_revert",
            "speech_keyboard_macros",
            "speech_clicking",
            "speech_keyboard_page_down",
            "speech_keyboard_volume_up",
            "speech_keyboard_right_arrow",
            "speech_keyboard_volume_down",
            "speech_start_transcribe",
            "joystick_triggers_left",
            "speech_hotkey_full_screen",
            "joystick_button_x",
            "speech_keyboard_switch",
            "speech_hotkey_save",
            "joystick_button_b",
            "speech_next_mode",
            "speech_hotkey_close",
            "speech_correction_mode_start",
            "speech_correction_mode_stop",
            "speech_keyboard_hashtag"
        ],
        "keyboard_hand": [
            "in_air_keyboard_click",
            "in_air_keyboard_active",
            "hand_mouse_switch_left_hand"
        ],
        "keyboard_hand_speech": [
            "in_air_keyboard_click",
            "speech_keyboard_windows_key",
            "speech_keyboard_cut",
            "speech_keyboard_copy",
            "speech_double_clicking",
            "speech_keyboard_escape",
            "speech_keyboard_space",
            "speech_stop_transcribe",
            "speech_right_clicking",
            "speech_keyboard_page_up",
            "speech_keyboard_windows_run",
            "speech_hotkey_print",
            "speech_keyboard_left_arrow",
            "speech_hotkey_paste",
            "speech_keyboard_help",
            "speech_hotkey_revert",
            "speech_keyboard_macros",
            "speech_clicking",
            "hand_mouse_switch_left_hand",
            "speech_keyboard_page_down",
            "speech_keyboard_volume_up",
            "in_air_keyboard_active",
            "speech_keyboard_right_arrow",
            "speech_keyboard_volume_down",
            "speech_start_transcribe",
            "speech_hotkey_full_screen",
            "speech_keyboard_switch",
            "speech_hotkey_save",
            "speech_next_mode",
            "speech_hotkey_close",
            "speech_correction_mode_start",
            "speech_correction_mode_stop",
            "speech_keyboard_hashtag"
        ],
        "left_fps_mode_1": [
            "hand_index_pinch_left_press_left_hand",
            "hand_middle_pinch_right_press_left_hand",
            "fps_mode_1_event",
            "hand_index_pulldown_left_press_left_hand",
            "hand_pinky_pinch_monitor_change_left_hand",
            "general_rocknroll_next_mode",
            "hand_palm_center_move_mouse_left_hand",
            "hand_fist_doubleclick_left_hand",
            "hand_palm_height_change_aoi_resize_left_hand",
            "hand_double_index_pinch_zoom",
            "hand_index_middle_scroll_left_hand"
        ],
        "left_fps_mode_1_speech": [
            "hand_index_pinch_left_press_left_hand",
            "speech_next_mode",
            "general_rocknroll_next_mode",
            "hand_pinky_pinch_monitor_change_left_hand",
            "speech_keyboard_windows_key",
            "speech_keyboard_cut",
            "speech_keyboard_copy",
            "speech_double_clicking",
            "fps_mode_1_event",
            "speech_keyboard_escape",
            "speech_keyboard_space",
            "speech_stop_transcribe",
            "speech_right_clicking",
            "speech_keyboard_page_up",
            "speech_keyboard_windows_run",
            "hand_middle_pinch_right_press_left_hand",
            "speech_hotkey_print",
            "hand_index_pulldown_left_press_left_hand",
            "speech_keyboard_left_arrow",
            "speech_hotkey_paste",
            "speech_keyboard_help",
            "speech_hotkey_revert",
            "speech_keyboard_macros",
            "speech_clicking",
            "hand_double_index_pinch_zoom",
            "speech_keyboard_page_down",
            "speech_keyboard_volume_up",
            "speech_keyboard_right_arrow",
            "speech_keyboard_volume_down",
            "speech_start_transcribe",
            "speech_hotkey_full_screen",
            "hand_palm_center_move_mouse_left_hand",
            "hand_fist_doubleclick_left_hand",
            "hand_palm_height_change_aoi_resize_left_hand",
            "speech_keyboard_switch",
            "speech_hotkey_save",
            "hand_index_middle_scroll_left_hand",
            "speech_hotkey_close",
            "speech_correction_mode_start",
            "speech_correction_mode_stop",
            "speech_keyboard_hashtag"
        ],
        "left_fps_mode_2": [
            "hand_index_pinch_left_press_left_hand",
            "hand_middle_pinch_right_press_left_hand",
            "hand_index_pulldown_left_press_left_hand",
            "fps_mode_2_event",
            "hand_pinky_pinch_monitor_change_left_hand",
            "general_rocknroll_next_mode",
            "hand_palm_center_move_mouse_left_hand",
            "hand_fist_doubleclick_left_hand",
            "hand_palm_height_change_aoi_resize_left_hand",
            "hand_double_index_pinch_zoom",
            "hand_index_middle_scroll_left_hand"
        ],
        "left_fps_mode_2_speech": [
            "hand_index_pinch_left_press_left_hand",
            "speech_next_mode",
            "general_rocknroll_next_mode",
            "hand_pinky_pinch_monitor_change_left_hand",
            "speech_keyboard_windows_key",
            "speech_keyboard_cut",
            "speech_keyboard_copy",
            "speech_double_clicking",
            "fps_mode_2_event",
            "speech_keyboard_escape",
            "speech_keyboard_space",
            "speech_stop_transcribe",
            "speech_right_clicking",
            "speech_keyboard_page_up",
            "speech_keyboard_windows_run",
            "hand_middle_pinch_right_press_left_hand",
            "speech_hotkey_print",
            "hand_index_pulldown_left_press_left_hand",
            "speech_keyboard_left_arrow",
            "speech_hotkey_paste",
            "speech_keyboard_help",
            "speech_hotkey_revert",
            "speech_keyboard_macros",
            "speech_clicking",
            "hand_double_index_pinch_zoom",
            "speech_keyboard_page_down",
            "speech_keyboard_volume_up",
            "speech_keyboard_right_arrow",
            "speech_keyboard_volume_down",
            "speech_start_transcribe",
            "speech_hotkey_full_screen",
            "hand_palm_center_move_mouse_left_hand",
            "hand_fist_doubleclick_left_hand",
            "hand_palm_height_change_aoi_resize_left_hand",
            "speech_keyboard_switch",
            "speech_hotkey_save",
            "hand_index_middle_scroll_left_hand",
            "speech_hotkey_close",
            "speech_correction_mode_start",
            "speech_correction_mode_stop",
            "speech_keyboard_hashtag"
        ],
        "left_fps_mode_3": [
            "hand_index_pinch_left_press_left_hand",
            "hand_middle_pinch_right_press_left_hand",
            "hand_index_pulldown_left_press_left_hand",
            "hand_pinky_pinch_monitor_change_left_hand",
            "general_rocknroll_next_mode",
            "hand_palm_center_move_mouse_left_hand",
            "hand_fist_doubleclick_left_hand",
            "hand_palm_height_change_aoi_resize_left_hand",
            "hand_double_index_pinch_zoom",
            "hand_index_middle_scroll_left_hand",
            "fps_mode_3_event"
        ],
        "left_fps_mode_3_speech": [
            "hand_index_pinch_left_press_left_hand",
            "speech_next_mode",
            "general_rocknroll_next_mode",
            "hand_pinky_pinch_monitor_change_left_hand",
            "speech_keyboard_windows_key",
            "speech_keyboard_cut",
            "speech_keyboard_copy",
            "speech_double_clicking",
            "speech_keyboard_escape",
            "speech_keyboard_space",
            "speech_stop_transcribe",
            "speech_right_clicking",
            "speech_keyboard_page_up",
            "speech_keyboard_windows_run",
            "hand_middle_pinch_right_press_left_hand",
            "speech_hotkey_print",
            "hand_index_pulldown_left_press_left_hand",
            "speech_keyboard_left_arrow",
            "speech_hotkey_paste",
            "speech_keyboard_help",
            "speech_hotkey_revert",
            "speech_keyboard_macros",
            "speech_clicking",
            "hand_double_index_pinch_zoom",
            "speech_keyboard_page_down",
            "speech_keyboard_volume_up",
            "speech_keyboard_right_arrow",
            "speech_keyboard_volume_down",
            "speech_start_transcribe",
            "speech_hotkey_full_screen",
            "hand_palm_center_move_mouse_left_hand",
            "hand_fist_doubleclick_left_hand",
            "hand_palm_height_change_aoi_resize_left_hand",
            "speech_keyboard_switch",
            "speech_hotkey_save",
            "hand_index_middle_scroll_left_hand",
            "speech_hotkey_close",
            "fps_mode_3_event",
            "speech_correction_mode_start",
            "speech_correction_mode_stop",
            "speech_keyboard_hashtag"
        ],
        "mr_swipe_left_hand": [
            "hand_mr_swipe_horizontal_left_hand",
            "hand_hand_hand_mr_swipe_horizontal_right_hand"
        ],
        "mr_swipe_right_hand": [
            "hand_mr_swipe_horizontal_right_hand",
            "hand_mr_swipe_vertical_right_hand"
        ],
        "nose_floating_facial": [
            "head_fishface_left_click",
            "head_raise_eyebrows_double_click",
            "general_rocknroll_next_mode",
            "head_smile_right_click",
            "head_nose_tracking",
            "head_open_mouth_left_press_hold_release"
        ],
        "nose_floating_speech": [
            "general_rocknroll_next_mode",
            "speech_keyboard_windows_key",
            "speech_keyboard_cut",
            "speech_keyboard_copy",
            "speech_double_clicking",
            "speech_keyboard_escape",
            "speech_keyboard_space",
            "speech_stop_transcribe",
            "speech_right_clicking",
            "speech_keyboard_page_up",
            "speech_keyboard_windows_run",
            "speech_hotkey_print",
            "speech_keyboard_left_arrow",
            "speech_hotkey_paste",
            "speech_keyboard_help",
            "speech_hotkey_revert",
            "speech_keyboard_macros",
            "speech_clicking",
            "speech_keyboard_page_down",
            "speech_keyboard_volume_up",
            "speech_keyboard_right_arrow",
            "speech_keyboard_volume_down",
            "speech_start_transcribe",
            "speech_hotkey_full_screen",
            "speech_keyboard_switch",
            "speech_hotkey_save",
            "head_nose_tracking",
            "speech_next_mode",
            "speech_hotkey_close",
            "speech_left_press",
            "speech_keyboard_enter",
            "speech_keyboard_up_arrow",
            "speech_keyboard_down_arrow",
            "speech_left_release",
            "speech_right_press",
            "speech_right_release",
            "speech_correction_mode_start",
            "speech_correction_mode_stop",
            "speech_change_language",
            "speech_start_speaker_identification",
            "speech_stop_speaker_identification",
            "speech_keyboard_hashtag"
        ],
        "nose_grid_facial": [
            "head_smile_left_press_hold_release",
            "head_fishface_left_click",
            "head_raise_eyebrows_double_click",
            "head_open_mouth_double_click",
            "head_left_rotation_left_click",
            "head_right_rotation_right_click",
            "speech_next_mode",
            "head_nose_scroll",
            "head_nose_direction_tracking_nosebox",
            "speech_head_nose_move_nosebox",
            "general_rocknroll_next_mode"
        ],
        "nose_grid_speech": [
            "general_rocknroll_next_mode",
            "head_nose_direction_tracking_nosebox",
            "speech_keyboard_windows_key",
            "speech_keyboard_cut",
            "speech_keyboard_copy",
            "head_raise_eyebrows_double_click",
            "speech_double_clicking",
            "speech_keyboard_escape",
            "speech_keyboard_space",
            "speech_stop_transcribe",
            "speech_head_nose_move_nosebox",
            "speech_keyboard_page_up",
            "speech_right_clicking",
            "speech_keyboard_windows_run",
            "speech_hotkey_print",
            "speech_keyboard_left_arrow",
            "speech_hotkey_paste",
            "speech_keyboard_help",
            "speech_hotkey_revert",
            "speech_keyboard_enter",
            "speech_keyboard_up_arrow",
            "speech_keyboard_down_arrow",
            "speech_keyboard_macros",
            "speech_clicking",
            "speech_keyboard_page_down",
            "speech_keyboard_volume_up",
            "speech_keyboard_right_arrow",
            "speech_keyboard_volume_down",
            "speech_start_transcribe",
            "speech_hotkey_full_screen",
            "speech_keyboard_switch",
            "speech_hotkey_save",
            "speech_eye_stop",
            "speech_next_mode",
            "speech_hotkey_close",
            "speech_left_press",
            "speech_left_release",
            "speech_right_press",
            "speech_right_release",
            "speech_head_nose_left_range_nosebox",
            "speech_head_nose_right_range_nosebox",
            "speech_head_nose_reset_nosebox",
            "speech_correction_mode_start",
            "speech_correction_mode_stop",
            "speech_start_speaker_identification",
            "speech_stop_speaker_identification",
            "speech_keyboard_hashtag"
        ],
        "pen_hand": [
            "general_rocknroll_next_mode",
            "pen_index_pinch_right_hand",
            "pen_active_right_hand",
            "pen_index_pinch_eraser_left_hand"
        ],
        "pen_hand_speech": [
            "pen_index_pinch_eraser_left_hand",
            "general_rocknroll_next_mode",
            "speech_keyboard_windows_key",
            "speech_keyboard_cut",
            "speech_keyboard_copy",
            "speech_double_clicking",
            "speech_keyboard_escape",
            "speech_keyboard_space",
            "speech_stop_transcribe",
            "speech_right_clicking",
            "speech_keyboard_page_up",
            "pen_index_pinch_right_hand",
            "speech_keyboard_windows_run",
            "speech_hotkey_print",
            "speech_keyboard_left_arrow",
            "speech_hotkey_paste",
            "speech_keyboard_help",
            "speech_hotkey_revert",
            "speech_keyboard_macros",
            "speech_clicking",
            "speech_keyboard_page_down",
            "speech_keyboard_volume_up",
            "speech_keyboard_right_arrow",
            "speech_keyboard_volume_down",
            "speech_start_transcribe",
            "speech_hotkey_full_screen",
            "speech_keyboard_switch",
            "speech_hotkey_save",
            "speech_next_mode",
            "speech_hotkey_close",
            "pen_active_right_hand",
            "speech_correction_mode_start",
            "speech_correction_mode_stop",
            "speech_keyboard_hashtag"
        ],
        "pen_hold_inking_right_hand": [
            "general_rocknroll_next_mode",
            "pen_pinch_hold_right_hand",
            "pen_active_right_hand",
            "pen_index_pinch_eraser_left_hand"
        ],
        "pen_hold_inking_right_hand_speech": [
            "pen_index_pinch_eraser_left_hand",
            "general_rocknroll_next_mode",
            "speech_keyboard_windows_key",
            "speech_keyboard_cut",
            "speech_keyboard_copy",
            "speech_double_clicking",
            "speech_keyboard_escape",
            "speech_keyboard_space",
            "speech_stop_transcribe",
            "speech_right_clicking",
            "speech_keyboard_page_up",
            "speech_keyboard_windows_run",
            "speech_hotkey_print",
            "speech_keyboard_left_arrow",
            "speech_hotkey_paste",
            "speech_keyboard_help",
            "speech_hotkey_revert",
            "speech_keyboard_macros",
            "speech_clicking",
            "speech_keyboard_page_down",
            "speech_keyboard_volume_up",
            "speech_keyboard_right_arrow",
            "speech_keyboard_volume_down",
            "speech_start_transcribe",
            "speech_hotkey_full_screen",
            "pen_pinch_hold_right_hand",
            "speech_keyboard_switch",
            "speech_hotkey_save",
            "speech_next_mode",
            "speech_hotkey_close",
            "pen_active_right_hand",
            "speech_correction_mode_start",
            "speech_correction_mode_stop",
            "speech_keyboard_hashtag"
        ],
        "right_fps_mode_1": [
            "fps_mode_1_event",
            "general_rocknroll_next_mode",
            "hand_index_pulldown_left_press_right_hand",
            "hand_pinky_pinch_monitor_change_right_hand",
            "hand_palm_center_move_mouse_right_hand",
            "hand_middle_pinch_right_press_right_hand",
            "hand_index_pinch_left_press_right_hand",
            "hand_double_index_pinch_zoom",
            "hand_fist_doubleclick_right_hand",
            "hand_palm_height_change_aoi_resize_right_hand",
            "hand_index_middle_scroll_right_hand"
        ],
        "right_fps_mode_1_speech": [
            "general_rocknroll_next_mode",
            "speech_keyboard_windows_key",
            "hand_palm_center_move_mouse_right_hand",
            "speech_keyboard_cut",
            "hand_middle_pinch_right_press_right_hand",
            "speech_keyboard_copy",
            "speech_double_clicking",
            "fps_mode_1_event",
            "speech_keyboard_escape",
            "speech_keyboard_space",
            "hand_pinky_pinch_monitor_change_right_hand",
            "speech_right_clicking",
            "speech_keyboard_page_up",
            "speech_stop_transcribe",
            "hand_palm_height_change_aoi_resize_right_hand",
            "speech_keyboard_windows_run",
            "speech_hotkey_print",
            "speech_keyboard_left_arrow",
            "speech_hotkey_paste",
            "speech_keyboard_help",
            "speech_hotkey_revert",
            "speech_keyboard_macros",
            "speech_clicking",
            "hand_index_pinch_left_press_right_hand",
            "hand_double_index_pinch_zoom",
            "hand_fist_doubleclick_right_hand",
            "speech_keyboard_page_down",
            "speech_keyboard_volume_up",
            "speech_keyboard_right_arrow",
            "speech_keyboard_volume_down",
            "speech_start_transcribe",
            "speech_hotkey_full_screen",
            "hand_index_pulldown_left_press_right_hand",
            "speech_keyboard_switch",
            "speech_hotkey_save",
            "speech_next_mode",
            "speech_hotkey_close",
            "hand_index_middle_scroll_right_hand",
            "speech_correction_mode_start",
            "speech_correction_mode_stop",
            "speech_keyboard_hashtag"
        ],
        "right_fps_mode_2": [
            "fps_mode_2_event",
            "general_rocknroll_next_mode",
            "hand_index_pulldown_left_press_right_hand",
            "hand_pinky_pinch_monitor_change_right_hand",
            "hand_palm_center_move_mouse_right_hand",
            "hand_middle_pinch_right_press_right_hand",
            "hand_index_pinch_left_press_right_hand",
            "hand_double_index_pinch_zoom",
            "hand_fist_doubleclick_right_hand",
            "hand_palm_height_change_aoi_resize_right_hand",
            "hand_index_middle_scroll_right_hand"
        ],
        "right_fps_mode_2_speech": [
            "general_rocknroll_next_mode",
            "speech_keyboard_windows_key",
            "hand_palm_center_move_mouse_right_hand",
            "speech_keyboard_cut",
            "hand_middle_pinch_right_press_right_hand",
            "speech_keyboard_copy",
            "speech_double_clicking",
            "fps_mode_2_event",
            "speech_keyboard_escape",
            "speech_keyboard_space",
            "hand_pinky_pinch_monitor_change_right_hand",
            "speech_right_clicking",
            "speech_keyboard_page_up",
            "speech_stop_transcribe",
            "hand_palm_height_change_aoi_resize_right_hand",
            "speech_keyboard_windows_run",
            "speech_hotkey_print",
            "speech_keyboard_left_arrow",
            "speech_hotkey_paste",
            "speech_keyboard_help",
            "speech_hotkey_revert",
            "speech_keyboard_macros",
            "speech_clicking",
            "hand_index_pinch_left_press_right_hand",
            "hand_double_index_pinch_zoom",
            "hand_fist_doubleclick_right_hand",
            "speech_keyboard_page_down",
            "speech_keyboard_volume_up",
            "speech_keyboard_right_arrow",
            "speech_keyboard_volume_down",
            "speech_start_transcribe",
            "speech_hotkey_full_screen",
            "hand_index_pulldown_left_press_right_hand",
            "speech_keyboard_switch",
            "speech_hotkey_save",
            "speech_next_mode",
            "speech_hotkey_close",
            "hand_index_middle_scroll_right_hand",
            "speech_correction_mode_start",
            "speech_correction_mode_stop",
            "speech_keyboard_hashtag"
        ],
        "right_fps_mode_3": [
            "general_rocknroll_next_mode",
            "hand_index_pulldown_left_press_right_hand",
            "hand_pinky_pinch_monitor_change_right_hand",
            "hand_palm_center_move_mouse_right_hand",
            "hand_middle_pinch_right_press_right_hand",
            "hand_index_pinch_left_press_right_hand",
            "fps_mode_3_event",
            "hand_double_index_pinch_zoom",
            "hand_fist_doubleclick_right_hand",
            "hand_palm_height_change_aoi_resize_right_hand",
            "hand_index_middle_scroll_right_hand"
        ],
        "right_fps_mode_3_speech": [
            "general_rocknroll_next_mode",
            "speech_keyboard_windows_key",
            "hand_palm_center_move_mouse_right_hand",
            "speech_keyboard_cut",
            "hand_middle_pinch_right_press_right_hand",
            "speech_keyboard_copy",
            "speech_double_clicking",
            "speech_keyboard_escape",
            "speech_keyboard_space",
            "hand_pinky_pinch_monitor_change_right_hand",
            "speech_right_clicking",
            "speech_keyboard_page_up",
            "speech_stop_transcribe",
            "hand_palm_height_change_aoi_resize_right_hand",
            "speech_keyboard_windows_run",
            "speech_hotkey_print",
            "speech_keyboard_left_arrow",
            "speech_hotkey_paste",
            "speech_keyboard_help",
            "hand_index_middle_scroll_right_hand",
            "speech_hotkey_revert",
            "speech_keyboard_macros",
            "speech_clicking",
            "hand_index_pinch_left_press_right_hand",
            "hand_double_index_pinch_zoom",
            "hand_fist_doubleclick_right_hand",
            "speech_keyboard_page_down",
            "speech_keyboard_volume_up",
            "speech_keyboard_right_arrow",
            "speech_keyboard_volume_down",
            "speech_start_transcribe",
            "speech_hotkey_full_screen",
            "hand_index_pulldown_left_press_right_hand",
            "speech_keyboard_switch",
            "speech_hotkey_save",
            "speech_next_mode",
            "speech_hotkey_close",
            "fps_mode_3_event",
            "speech_correction_mode_start",
            "speech_correction_mode_stop",
            "speech_keyboard_hashtag"
        ],
        "samurai_swipe": [
            "hand_samurai_swipe"
        ],
        "speech": [
            "general_rocknroll_next_mode",
            "speech_keyboard_windows_key",
            "speech_keyboard_cut",
            "speech_keyboard_copy",
            "speech_double_clicking",
            "speech_keyboard_escape",
            "speech_keyboard_space",
            "speech_stop_transcribe",
            "speech_right_clicking",
            "speech_keyboard_page_up",
            "speech_keyboard_windows_run",
            "speech_hotkey_print",
            "speech_keyboard_left_arrow",
            "speech_hotkey_paste",
            "speech_keyboard_help",
            "speech_hotkey_revert",
            "speech_keyboard_macros",
            "speech_clicking",
            "speech_keyboard_page_down",
            "speech_keyboard_volume_up",
            "speech_keyboard_right_arrow",
            "speech_keyboard_volume_down",
            "speech_start_transcribe",
            "speech_hotkey_full_screen",
            "speech_keyboard_switch",
            "speech_hotkey_save",
            "speech_next_mode",
            "speech_hotkey_close",
            "speech_correction_mode_start",
            "speech_correction_mode_stop",
            "speech_keyboard_hashtag"
        ],
        "touchpoints_hand": [
            "hand_index_pinch_touch_press_right_hand",
            "hand_middle_pinch_left_click_right_hand",
            "hand_palm_center_move_touch_right_hand",
            "hand_palm_height_change_aoi_resize_right_hand",
            "hand_pinky_pinch_monitor_change_left_hand",
            "hand_pinky_pinch_right_click_right_hand",
            "hand_ring_pinch_double_click_right_hand",
            "general_rocknroll_next_mode",
            "speech_next_mode"
        ],
        "touchpoints_hand_speech": [
            "general_rocknroll_next_mode",
            "speech_keyboard_windows_key",
            "hand_middle_pinch_left_click_left_hand",
            "speech_keyboard_cut",
            "speech_keyboard_copy",
            "hand_pinky_pinch_right_click_left_hand",
            "speech_double_clicking",
            "hand_ring_pinch_double_click_left_hand",
            "speech_keyboard_escape",
            "speech_keyboard_space",
            "hand_pinky_pinch_monitor_change_right_hand",
            "speech_right_clicking",
            "speech_keyboard_page_up",
            "speech_stop_transcribe",
            "speech_keyboard_windows_run",
            "speech_hotkey_print",
            "hand_palm_center_move_touch_left_hand",
            "speech_keyboard_left_arrow",
            "speech_hotkey_paste",
            "speech_keyboard_help",
            "speech_hotkey_revert",
            "speech_keyboard_macros",
            "speech_clicking",
            "speech_keyboard_page_down",
            "speech_keyboard_volume_up",
            "speech_keyboard_right_arrow",
            "speech_keyboard_volume_down",
            "speech_start_transcribe",
            "speech_hotkey_full_screen",
            "hand_palm_height_change_aoi_resize_left_hand",
            "speech_keyboard_switch",
            "speech_hotkey_save",
            "hand_index_pinch_touch_press_left_hand",
            "speech_next_mode",
            "speech_hotkey_close",
            "speech_left_press",
            "speech_left_release",
            "speech_right_press",
            "speech_right_release",
            "speech_correction_mode_start",
            "speech_correction_mode_stop",
            "speech_start_speaker_identification",
            "speech_stop_speaker_identification",
            "speech_keyboard_hashtag"
        ],
        "touchpoints_left_hand_speech": [
            "hand_pinky_pinch_triple_swipe_right_hand",
            "hand_index_pinch_touch_press_left_hand",
            "hand_double_pinch_left_press_right_hand",
            "hand_ring_pinch_right_press_right_hand",
            "hand_palm_center_move_touch_left_hand",
            "hand_palm_height_change_aoi_resize_left_hand",
            "hand_pinky_pinch_right_click_left_hand",
            "hand_rabbit_monitor_change_right_hand",
            "hand_ring_pinch_double_click_left_hand",
            "hand_middle_pinch_left_click_left_hand",
            "speech_keyboard_windows_key",
            "speech_keyboard_left_arrow",
            "speech_double_clicking",
            "speech_hotkey_paste",
            "speech_keyboard_space",
            "speech_keyboard_switch",
            "speech_keyboard_macros",
            "speech_hotkey_full_screen",
            "speech_right_clicking",
            "speech_keyboard_copy",
            "speech_right_release",
            "speech_hotkey_window_minimize",
            "speech_hotkey_windows_screenshot",
            "speech_hotkey_revert",
            "speech_keyboard_page_up",
            "speech_keyboard_windows_run",
            "speech_keyboard_page_down",
            "speech_hotkey_print",
            "speech_keyboard_help",
            "speech_hotkey_window_maximize_left",
            "speech_keyboard_windows_startmenu",
            "speech_right_press",
            "speech_keyboard_right_arrow",
            "speech_hotkey_close",
            "speech_left_press",
            "speech_clicking",
            "speech_keyboard_cut",
            "speech_stop_transcribe",
            "speech_hotkey_save",
            "speech_hotkey_window_maximize_right",
            "speech_hotkey_windows_explorer_files",
            "speech_keyboard_escape",
            "speech_hotkey_window_maximize",
            "speech_start_transcribe",
            "speech_change_language",
            "speech_keyboard_volume_down",
            "speech_left_release",
            "speech_keyboard_volume_up",
            "speech_next_mode",
            "speech_correction_mode_start",
            "speech_correction_mode_stop",
            "speech_start_speaker_identification",
            "speech_stop_speaker_identification",
            "speech_keyboard_backspace",
            "speech_keyboard_capital_letters",
            "speech_keyboard_hashtag",
            "speech_keyboard_settings",
            "speech_hotkey_go_left",
            "speech_hotkey_go_right",
            "speech_hotkey_remove"
        ],
        "touchpoints_right_hand_speech": [
            "hand_pinky_pinch_triple_swipe_left_hand",
            "hand_index_pinch_touch_press_right_hand",
            "hand_double_pinch_left_press_left_hand",
            "hand_ring_pinch_right_press_left_hand",
            "hand_palm_center_move_touch_right_hand",
            "hand_palm_height_change_aoi_resize_right_hand",
            "hand_pinky_pinch_right_click_right_hand",
            "hand_rabbit_monitor_change_left_hand",
            "hand_ring_pinch_double_click_right_hand",
            "hand_middle_pinch_left_click_right_hand",
            "speech_start_transcribe",
            "speech_stop_transcribe",
            "speech_change_language",
            "speech_correction_mode_start",
            "speech_correction_mode_stop",
            "speech_start_speaker_identification",
            "speech_stop_speaker_identification",
            "speech_remove_locked_speaker",
            "speech_enable_speaker_identify",
            "speech_disable_speaker_identify",
            "speech_next_mode",
            "speech_keyboard_switch",
            "speech_keyboard_windows_key",
            "speech_keyboard_macros",
            "speech_keyboard_windows_run",
            "speech_hotkey_full_screen",
            "speech_hotkey_window_maximize",
            "speech_hotkey_window_minimize",
            "speech_hotkey_window_maximize_left",
            "speech_hotkey_window_maximize_right",
            "speech_keyboard_windows_startmenu",
            "speech_hotkey_windows_explorer_files",
            "speech_hotkey_windows_screenshot",
            "speech_clicking",
            "speech_double_clicking",
            "speech_right_clicking",
            "speech_left_release",
            "speech_right_release",
            "speech_keyboard_page_up",
            "speech_keyboard_page_down",
            "speech_keyboard_up_arrow",
            "speech_keyboard_down_arrow",
            "speech_keyboard_left_arrow",
            "speech_keyboard_right_arrow",
            "speech_keyboard_copy",
            "speech_hotkey_paste",
            "speech_keyboard_cut",
            "speech_hotkey_save",
            "speech_hotkey_revert",
            "speech_keyboard_space",
            "speech_hotkey_print",
            "speech_keyboard_help",
            "speech_hotkey_close",
            "speech_keyboard_escape",
            "speech_keyboard_volume_up",
            "speech_keyboard_volume_down",
            "speech_keyboard_backspace",
            "speech_keyboard_capital_letters",
            "speech_hotkey_teams_mute",
            "speech_keyboard_hashtag",
            "speech_keyboard_settings",
            "speech_hotkey_go_left",
            "speech_hotkey_go_right",
            "speech_hotkey_remove"
        ],
        "vs_nose_grid_speech": [
            "general_rocknroll_next_mode",
            "head_nose_direction_tracking_nosebox",
            "speech_keyboard_windows_key",
            "head_raise_eyebrows_double_click",
            "speech_double_clicking",
            "speech_start_transcribe",
            "speech_stop_transcribe",
            "speech_head_nose_move_nosebox",
            "speech_right_clicking",
            "speech_keyboard_windows_run",
            "speech_hotkey_print",
            "speech_keyboard_enter",
            "speech_keyboard_macros",
            "speech_clicking",
            "speech_hotkey_full_screen",
            "speech_keyboard_switch",
            "speech_eye_stop",
            "speech_next_mode",
            "speech_left_press",
            "speech_left_release",
            "speech_right_press",
            "speech_right_release",
            "speech_head_nose_left_range_nosebox",
            "speech_head_nose_right_range_nosebox",
            "speech_head_nose_reset_nosebox",
            "speech_correction_mode_start",
            "speech_correction_mode_stop",
            "speech_keyboard_help",
            "speech_keyboard_copy",
            "speech_hotkey_paste",
            "speech_keyboard_cut",
            "speech_hotkey_save",
            "speech_hotkey_revert",
            "speech_hotkey_go_left",
            "speech_hotkey_go_right",
            "speech_hotkey_remove",
            "speech_keyboard_hashtag",
            "speech_keyboard_escape",
            "speech_hotkey_close",
            "speech_keyboard_space",
            "speech_keyboard_backspace",
            "speech_keyboard_capital_letters",
            "speech_keyboard_page_up",
            "speech_keyboard_page_down",
            "speech_keyboard_volume_up",
            "speech_keyboard_volume_down",
            "speech_keyboard_up_arrow",
            "speech_keyboard_down_arrow",
            "speech_keyboard_left_arrow",
            "speech_keyboard_right_arrow",
            "speech_hotkey_window_maximize",
            "speech_hotkey_window_minimize",
            "speech_hotkey_window_maximize_left",
            "speech_hotkey_window_maximize_right",
            "speech_keyboard_windows_startmenu",
            "speech_hotkey_windows_explorer_files",
            "speech_hotkey_windows_screenshot",
            "speech_hotkey_vs_redo",
            "speech_hotkey_vs_find",
            "speech_hotkey_vs_new_file",
            "speech_hotkey_vs_open_file",
            "speech_hotkey_vs_new_project",
            "speech_hotkey_vs_open_project",
            "speech_hotkey_vs_go_to_line",
            "speech_hotkey_vs_comment_line",
            "speech_hotkey_vs_build_solution",
            "speech_hotkey_vs_start_debug",
            "speech_hotkey_vs_stop_debug",
            "speech_hotkey_vs_start_without_debug",
            "speech_hotkey_vs_save_all_files",
            "speech_hotkey_vs_cancel_selection",
            "speech_hotkey_vs_cancel_process",
            "speech_hotkey_vs_find_files",
            "speech_hotkey_vs_finding_files",
            "speech_hotkey_vs_solution_explorer",
            "speech_hotkey_vs_output_window",
            "speech_hotkey_vs_replace",
            "speech_hotkey_vs_rename",
            "speech_hotkey_vs_show_exceptions",
            "speech_hotkey_vs_compile",
            "speech_keyboard_vs_visual_guidance_open_all_windows",
            "speech_keyboard_vs_visual_guidance_maximize",
            "speech_keyboard_vs_visual_guidance_minimize",
            "speech_keyboard_vs_visual_guidance_zoom_in",
            "speech_keyboard_vs_visual_guidance_zoom_out",
            "speech_keyboard_vs_visual_guidance_reset_zoom",
            "speech_keyboard_vs_visual_guidance_insert_to_editor",
            "speech_keyboard_vs_visual_guidance_copy_to_clipboard",
            "general_rocknroll_next_mode",
            "head_nose_direction_tracking_nosebox",
            "head_raise_eyebrows_double_click",
            "speech_double_clicking",
            "speech_right_clicking",
            "speech_eye_stop",
            "speech_next_mode",
            "speech_clicking",
            "speech_left_press",
            "speech_left_release",
            "speech_right_press",
            "speech_right_release",
            "speech_head_nose_left_range_nosebox",
            "speech_head_nose_right_range_nosebox",
            "speech_head_nose_reset_nosebox"
        ]
    }
}
